{"dependencies":[{"name":"reason-react/lib/js/src/ReasonReact.js","loc":{"line":4,"column":34}},{"name":"./JsxComponent1.bs.js","loc":{"line":5,"column":34}}],"generated":{"js":"// Generated by BUCKLESCRIPT VERSION 2.1.0, PLEASE EDIT WITH CARE\n'use strict';\n\nvar ReasonReact = require(\"reason-react/lib/js/src/ReasonReact.js\");\nvar JsxComponent1$Test7 = require(\"./JsxComponent1.bs.js\");\n\nvar component = ReasonReact.statelessComponent(\"TodoApp\");\n\nfunction make() {\n  var newrecord = component.slice();\n  newrecord[/* render */9] = function () {\n    return ReasonReact.element( /* None */0, /* None */0, JsxComponent1$Test7.make( /* array */[]));\n  };\n  return newrecord;\n}\n\nexports.component = component;\nexports.make = make;\n/* component Not a pure module */"},"hash":"f4cda98ea63c097d22092c1306ee2445"}